json_model/README.md
json_model/__init__.py
json_model/analyze.py
json_model/clang.py
json_model/convert.py
json_model/export.py
json_model/irep.py
json_model/java.py
json_model/javascript.py
json_model/language.py
json_model/model.py
json_model/mtypes.py
json_model/objmerge.py
json_model/optim.py
json_model/perl.py
json_model/plpgsql.py
json_model/python.py
json_model/recurse.py
json_model/resolver.py
json_model/script.py
json_model/url_cache.py
json_model/utils.py
json_model/xstatic.py
json_model/data/clang_entry.c
json_model/data/clang_free.c
json_model/data/clang_init.c
json_model/data/clang_pcre2_fun.c
json_model/data/clang_re2_fun.c
json_model/data/java_free.java
json_model/data/java_init.java
json_model/data/javascript_exe.js
json_model/data/javascript_foot.js
json_model/data/javascript_free.js
json_model/data/javascript_head.js
json_model/data/javascript_init.js
json_model/data/javascript_main.js
json_model/data/jmc.pod
json_model/data/perl_entry.pl
json_model/data/perl_exe.pl
json_model/data/perl_free.pl
json_model/data/perl_init.pl
json_model/data/perl_main.pl
json_model/data/perl_pkg.pl
json_model/data/plpgsql_entry.sql
json_model/data/python_entry.py
json_model/data/python_exe.py
json_model/data/python_free.py
json_model/data/python_init.py
json_model/data/python_main.py
json_model/runtime/Makefile
json_model/runtime/__init__.py
json_model/runtime/support.py
json_model/runtime/types.py
json_model/runtime/c/Makefile
json_model/runtime/c/json-model.c
json_model/runtime/c/json-model.h
json_model/runtime/c/main.c
json_model/runtime/java/.gitignore
json_model/runtime/java/Makefile
json_model/runtime/java/README.md
json_model/runtime/java/env.bash
json_model/runtime/java/pom.xml
json_model/runtime/java/json_model/Checker.java
json_model/runtime/java/json_model/GSON.java
json_model/runtime/java/json_model/JSON.java
json_model/runtime/java/json_model/JSONP.java
json_model/runtime/java/json_model/Jackson.java
json_model/runtime/java/json_model/Main.java
json_model_compiler-2.0b36.dist-info/METADATA
json_model_compiler-2.0b36.dist-info/WHEEL
json_model_compiler-2.0b36.dist-info/entry_points.txt
json_model_compiler-2.0b36.dist-info/top_level.txt
json_model_compiler-2.0b36.dist-info/RECORD
