Metadata-Version: 2.4
Name: json_model_compiler
Version: 2.0b36
Summary: JSON Model Tools
Author: Fabien Coelho, Claire Yannou-Medrala
License-Expression: CC0-1.0
Project-URL: homepage, https://json-model.org/
Project-URL: documentation, https://json-model.org/
Project-URL: repository, https://github.com/clairey-zx81/json-model.git
Project-URL: issues, https://github.com/clairey-zx81/json-model/issues
Classifier: Topic :: Software Development
Requires-Python: >=3.12
Requires-Dist: requests
Requires-Dist: google-re2
Requires-Dist: pyyaml
Requires-Dist: validators
Requires-Dist: json-schema-utils>=0.8.5
Provides-Extra: dev
Requires-Dist: flake8; extra == "dev"
Requires-Dist: ruff; extra == "dev"
Requires-Dist: pyright; extra == "dev"
Requires-Dist: pytest; extra == "dev"
Requires-Dist: pytest-xdist[psutils]; extra == "dev"
Requires-Dist: filelock; extra == "dev"
Requires-Dist: ipython; extra == "dev"
Provides-Extra: dist
Requires-Dist: build; extra == "dist"
Requires-Dist: wheel; extra == "dist"
Requires-Dist: twine; extra == "dist"
